justernetes/__init__.py
justernetes/cli.py
justernetes/crd.py
justernetes/logging.py
justernetes/settings.py
justernetes-0.1.6.dist-info/METADATA
justernetes-0.1.6.dist-info/WHEEL
justernetes-0.1.6.dist-info/entry_points.txt
justernetes-0.1.6.dist-info/RECORD
