Metadata-Version: 2.3
Name: justernetes
Version: 0.1.6
Summary: 
Author: knspar
Author-email: knspar@proton.me
Requires-Python: >=3.12,<4.0
Classifier: Programming Language :: Python :: 3
Classifier: Programming Language :: Python :: 3.12
Classifier: Programming Language :: Python :: 3.13
Requires-Dist: dynaconf (>=3.2.11,<4.0.0)
Requires-Dist: kopf (>=1.38.0,<2.0.0)
Requires-Dist: kubernetes (>=33.1.0,<34.0.0)
Requires-Dist: loguru (>=0.7.3,<0.8.0)
Requires-Dist: pydantic (>=2.11.5,<3.0.0)
Requires-Dist: requests (>=2.32.4,<3.0.0)
Requires-Dist: typer (>=0.16.0,<0.17.0)
